cheetah_spi/__init__.py
cheetah_spi/cheetah.dll
cheetah_spi-0.1.0.dist-info/METADATA
cheetah_spi-0.1.0.dist-info/WHEEL
cheetah_spi-0.1.0.dist-info/top_level.txt
cheetah_spi-0.1.0.dist-info/RECORD
